data_manager_app/__init__.py
data_manager_app/admin.py
data_manager_app/admin_site.py
data_manager_app/apps.py
data_manager_app/consents.py
data_manager_app/lab_profiles.py
data_manager_app/models.py
data_manager_app/navbars.py
data_manager_app/sites.py
data_manager_app/urls.py
data_manager_app/views.py
data_manager_app/visit_schedules.py
data_manager_app/templates/data_manager_app/home.html
edc_data_manager/__init__.py
edc_data_manager/action_items.py
edc_data_manager/admin_site.py
edc_data_manager/apps.py
edc_data_manager/auth_objects.py
edc_data_manager/auths.py
edc_data_manager/baker_recipes.py
edc_data_manager/choices.py
edc_data_manager/constants.py
edc_data_manager/data_manager.py
edc_data_manager/get_data_queries.py
edc_data_manager/get_longitudinal_value.py
edc_data_manager/manage.py
edc_data_manager/navbar_item.py
edc_data_manager/populate_data_dictionary.py
edc_data_manager/post_migrate_signals.py
edc_data_manager/site_data_manager.py
edc_data_manager/tasks.py
edc_data_manager/urls.py
edc_data_manager/admin/__init__.py
edc_data_manager/admin/action_item_admin.py
edc_data_manager/admin/actions.py
edc_data_manager/admin/autocomplete_admin.py
edc_data_manager/admin/data_dictionary_admin.py
edc_data_manager/admin/data_query_admin.py
edc_data_manager/admin/issue_admin.py
edc_data_manager/admin/query_rule_admin.py
edc_data_manager/forms/__init__.py
edc_data_manager/forms/data_dictionary.py
edc_data_manager/forms/data_query.py
edc_data_manager/forms/query_rule.py
edc_data_manager/handlers/__init__.py
edc_data_manager/handlers/handlers.py
edc_data_manager/management/__init__.py
edc_data_manager/management/commands/__init__.py
edc_data_manager/management/commands/run_query_rules.py
edc_data_manager/migrations/0001_initial.py
edc_data_manager/migrations/0002_auto_20190725_1822.py
edc_data_manager/migrations/0003_auto_20190806_1749.py
edc_data_manager/migrations/0004_auto_20190806_1750.py
edc_data_manager/migrations/0005_auto_20190826_1646.py
edc_data_manager-1.0.0.dist-info/licenses/AUTHORS.rst
edc_data_manager-1.0.0.dist-info/licenses/LICENSE
edc_data_manager-1.0.0.dist-info/METADATA
edc_data_manager-1.0.0.dist-info/WHEEL
edc_data_manager-1.0.0.dist-info/top_level.txt
edc_data_manager-1.0.0.dist-info/RECORD
