Metadata-Version: 2.4
Name: edc-data-manager
Version: 1.0.0
Summary: Data manager administrative models and classes for clinicedc/edc projects
Home-page: https://github.com/clinicedc/edc-data-manager
Author: Erik van Widenfelt
Author-email: ew2789@gmail.com
License: GPL license, see LICENSE
Keywords: django Edc,data management,CRF,clinicedc,clinical trials
Classifier: Environment :: Web Environment
Classifier: Framework :: Django
Classifier: Framework :: Django :: 5.1
Classifier: Intended Audience :: Developers
Classifier: Intended Audience :: Science/Research
Classifier: Operating System :: OS Independent
Classifier: Programming Language :: Python :: 3.12
Classifier: License :: OSI Approved :: GNU General Public License v3 (GPLv3)
Requires-Python: >=3.12
License-File: LICENSE
License-File: AUTHORS.rst
Requires-Dist: arrow
Requires-Dist: celery
Provides-Extra: test
Requires-Dist: django_webtest; extra == "test"
Dynamic: license-file
